{
	"format_version": "1.8.0",
	"animations": {
		"animation.mouse.idle": {
			"animation_length": 12.6,
			"bones": {
				"wholebody": {
					"position": {
						"vector": [0, "math.sin(query.anim_time*350)*0.5", 0]
					}
				},
				"ear2": {
					"rotation": {
						"vector": [0, 0, "math.sin(query.anim_time*350)*3.5"]
					}
				},
				"ear3": {
					"rotation": {
						"vector": [0, 0, "math.sin(query.anim_time*350)*3.5"]
					}
				},
				"whisker2": {
					"rotation": {
						"vector": ["-math.sin(query.anim_time*350)*10", 0, 0]
					}
				},
				"whisker1": {
					"rotation": {
						"vector": ["-math.sin(query.anim_time*350)*6", 0, 5]
					},
					"position": {
						"vector": [0, 0, 0]
					}
				},
				"tail": {
					"rotation": {
						"vector": [0, 0, "math.sin(query.anim_time*350)*15"]
					}
				},
				"topofhead": {
					"rotation": {
						"vector": [0, 0, "math.sin(query.anim_time*350)*10"]
					}
				},
				"nose": {
					"rotation": {
						"vector": ["1-math.sin(query.anim_time*350)*5", 0, 0]
					}
				},
				"cheek1": {
					"position": {
						"vector": [1, 0, 0]
					},
					"scale": {
						"vector": ["1+math.cos(query.anim_time*350)*0.2", 1, 1]
					}
				},
				"cheek2": {
					"position": {
						"vector": [-1, 0, 0]
					},
					"scale": {
						"vector": ["1+math.cos(query.anim_time*350)*0.2", 1, 1]
					}
				},
				"hand2": {
					"rotation": {
						"vector": [0, 75, -55]
					},
					"position": {
						"vector": [-2.25, 0, -1]
					}
				},
				"hand3": {
					"rotation": {
						"vector": [0, -70, 55]
					},
					"position": {
						"vector": [3, 0.25, -1]
					}
				}
			}
		},
		"animation.mouse.sitting": {
			"animation_length": 7.72,
			"bones": {
				"wholebody": {
					"position": {
						"vector": [0, -2, 0]
					}
				},
				"hand2": {
					"rotation": {
						"vector": [27.5, 47.5, -25]
					},
					"position": {
						"vector": [-3, -2, -1]
					}
				},
				"leg1": {
					"rotation": {
						"vector": [0, 25, 0]
					},
					"position": {
						"vector": [1, 0, -3]
					}
				},
				"leg2": {
					"rotation": {
						"vector": [0, -25, 0]
					},
					"position": {
						"vector": [-1, 0, -3]
					}
				},
				"legs": {
					"rotation": {
						"vector": [0, 0, 0]
					}
				},
				"body": {
					"position": {
						"vector": [0, "math.sin(query.anim_time*150)*0.4", 0]
					}
				},
				"head": {
					"position": {
						"vector": [0, "math.sin(query.anim_time*150)*0.4", 0]
					}
				},
				"ear2": {
					"rotation": {
						"vector": [0, 0, "math.sin(query.anim_time*150)*5"]
					}
				},
				"ear3": {
					"rotation": {
						"vector": [0, 0, "math.sin(query.anim_time*150)*5"]
					}
				},
				"whisker2": {
					"rotation": {
						"vector": [0, 0, "math.sin(query.anim_time*150)*5"]
					}
				},
				"whisker1": {
					"rotation": {
						"vector": [0, 0, "math.sin(query.anim_time*150)*5"]
					}
				},
				"tail": {
					"rotation": {
						"vector": [0, 0, "math.sin(query.anim_time*150)*15"]
					},
					"position": {
						"vector": [0, "math.sin(query.anim_time*150)*0.4", 0]
					}
				},
				"topofhead": {
					"rotation": {
						"vector": [0, 0, "math.sin(query.anim_time*150)*10"]
					}
				},
				"nose": {
					"rotation": {
						"vector": ["math.sin(query.anim_time*150)*5", 0, 0]
					}
				},
				"cheek1": {
					"position": {
						"vector": [1, 0, 0]
					},
					"scale": {
						"vector": ["1+math.cos(query.anim_time*150)*0.2", 1, 1]
					}
				},
				"cheek2": {
					"position": {
						"vector": [-1, 0, 0]
					},
					"scale": {
						"vector": ["1+math.cos(query.anim_time*150)*0.2", 1, 1]
					}
				},
				"hand3": {
					"rotation": {
						"vector": [35, -42.5, 15]
					},
					"position": {
						"vector": [3, -2, -1]
					}
				}
			}
		},
		"animation.mouse.running": {
			"loop": true,
			"bones": {
				"wholebody": {
					"rotation": {
						"vector": [90, 0, 0]
					},
					"position": {
						"vector": [0, "-2-math.sin(query.anim_time*1000)*4", "math.sin(query.anim_time*1000)*4"]
					}
				},
				"body": {
					"position": {
						"vector": [0, 1, 0]
					}
				},
				"head": {
					"rotation": {
						"vector": ["-90+math.sin(query.anim_time*1000)*10", 0, 0]
					},
					"position": {
						"vector": [0, 5.6, -5]
					}
				},
				"ear2": {
					"rotation": {
						"vector": [12.5, "22.5-math.sin(query.anim_time*1000)*20", 0]
					},
					"position": {
						"vector": [0, 0, -6]
					}
				},
				"ear3": {
					"rotation": {
						"vector": [2.5, "17.5-math.sin(query.anim_time*1000)*20", -2.5]
					},
					"position": {
						"vector": [0, 0, -4]
					}
				},
				"whisker2": {
					"rotation": {
						"vector": [0, "-math.sin(query.anim_time*1000)*30", 0]
					}
				},
				"whisker1": {
					"rotation": {
						"vector": [0, "math.sin(query.anim_time*1000)*30", 0]
					}
				},
				"topofhead": {
					"rotation": {
						"vector": ["math.sin(query.anim_time*1000)*30", 0, 0]
					}
				},
				"nose": {
					"rotation": {
						"vector": ["-math.sin(query.anim_time*1000)*60", 0, 0]
					}
				},
				"tail": {
					"rotation": {
						"vector": ["-135+math.sin(query.anim_time*1000)*30", 0, 0]
					},
					"position": {
						"vector": [0, -2, -3]
					}
				},
				"hand2": {
					"rotation": {
						"vector": ["math.sin(query.anim_time*1000)*60", 0, 0]
					},
					"position": {
						"vector": [-5, 8, 0.1]
					}
				},
				"legs": {
					"rotation": {
						"vector": [0, 0, 0]
					},
					"position": {
						"vector": [0, "2-math.sin(query.anim_time*1000)*4", "math.sin(query.anim_time*1000)*4"]
					}
				},
				"leg2": {
					"rotation": {
						"vector": ["-math.sin(query.anim_time*1000)*30", 0, 0]
					},
					"position": {
						"vector": [0, 0, 6]
					}
				},
				"leg1": {
					"rotation": {
						"vector": ["-math.sin(query.anim_time*1000)*30", 0, 0]
					},
					"position": {
						"vector": [0, 0, 6]
					}
				},
				"hand3": {
					"rotation": {
						"vector": ["math.sin(query.anim_time*1000)*60", 0, 0]
					},
					"position": {
						"vector": [4, 8, 0]
					}
				}
			}
		}
	},
	"geckolib_format_version": 2
}